boxplot/__init__.py
boxplot/boxplot.py
boxplot-0.1.1.dist-info/METADATA
boxplot-0.1.1.dist-info/WHEEL
boxplot-0.1.1.dist-info/top_level.txt
boxplot-0.1.1.dist-info/RECORD
