Metadata-Version: 2.4
Name: boxplot
Version: 0.1.1
Summary: Boxplot de forma simples
Home-page: https://github.com/nukhes/boxplot
Author: nukhes
Author-email: nukhes <nukhes@protonmail.com>
Classifier: Programming Language :: Python :: 3
Classifier: Programming Language :: Python :: 3.9
Classifier: License :: OSI Approved :: MIT License
Classifier: Operating System :: OS Independent
Classifier: Intended Audience :: Developers
Classifier: Topic :: Scientific/Engineering :: Information Analysis
Requires-Python: >=3.9
Dynamic: author
Dynamic: home-page
Dynamic: requires-python
